ticinfo/__init__.py
ticinfo/toco.py
ticinfo-0.4.5.dist-info/LICENSE
ticinfo-0.4.5.dist-info/METADATA
ticinfo-0.4.5.dist-info/WHEEL
ticinfo-0.4.5.dist-info/entry_points.txt
ticinfo-0.4.5.dist-info/RECORD
