Metadata-Version: 2.1
Name: ticinfo
Version: 0.4.5
Summary: quick information on TESS targets
License: MIT
Author: TESS Science Support Center
Author-email: tesshelp@bigbang.gsfc.nasa.gov
Requires-Python: >=3.9,<4.0
Classifier: License :: OSI Approved :: MIT License
Classifier: Programming Language :: Python :: 3
Classifier: Programming Language :: Python :: 3.9
Classifier: Programming Language :: Python :: 3.10
Classifier: Programming Language :: Python :: 3.11
Classifier: Programming Language :: Python :: 3.12
Classifier: Programming Language :: Python :: 3.13
Requires-Dist: astropy (>=5.0.0)
Requires-Dist: astroquery (>=0.4.6)
Requires-Dist: rich (>=13.7.0,<14.0.0)
Requires-Dist: tesswcs (>=1.1.2,<2.0.0)
